day_3/lab_03_vga/vga.sv
// Asynchronous reset here is needed for the FPGA board we use

module vga
# (
    parameter N_MIXER_PIPE_STAGES = 0,

              HPOS_WIDTH          = 10,
              VPOS_WIDTH          = 10,

              // Horizontal constants

              H_DISPLAY           = 640,  // Horizontal display width
              H_FRONT             =  16,  // Horizontal right border (front porch)
              H_SYNC              =  96,  // Horizontal sync width
              H_BACK              =  48,  // Horizontal left border (back porch)

              // Vertical constants

              V_DISPLAY           = 480,  // Vertical display height
              V_BOTTOM            =  10,  // Vertical bottom border
              V_SYNC              =   2,  // Vertical sync # lines
              V_TOP               =  33,  // Vertical top border
              
              CLK_MHZ             =  50,   // Clock frequency (50 or 100 MHz)
              VGA_CLOCK           =  25   // Pixel clock of VGA in MHz
)
(
    input                           clk,
    input                           reset,
    output logic                    hsync,
    output logic                    vsync,
    output logic                    display_on,
    output logic [HPOS_WIDTH - 1:0] hpos,
    output logic [VPOS_WIDTH - 1:0] vpos
);

    // Derived constants

    localparam H_SYNC_START  = H_DISPLAY    + H_FRONT + N_MIXER_PIPE_STAGES,
               H_SYNC_END    = H_SYNC_START + H_SYNC  - 1,
               H_MAX         = H_SYNC_END   + H_BACK,

               V_SYNC_START  = V_DISPLAY    + V_BOTTOM,
               V_SYNC_END    = V_SYNC_START + V_SYNC  - 1,
               V_MAX         = V_SYNC_END   + V_TOP;

    // Calculating next values of the counters

    logic [HPOS_WIDTH - 1:0] d_hpos;
    logic [VPOS_WIDTH - 1:0] d_vpos;

    always_comb
    begin
        if (hpos == H_MAX)
        begin
            d_hpos = 1'd0;

            if (vpos == V_MAX)
                d_vpos = 1'd0;
            else
                d_vpos = vpos + 1'd1;
        end
        else
        begin
          d_hpos = hpos + 1'd1;
          d_vpos = vpos;
        end
    end

    // Enable to divide clock from 50 or 100 MHz to 25 MHz

    logic [3:0] clk_en_cnt;
    logic clk_en;

    always_ff @ (posedge clk or posedge reset)
    begin
        if (reset)
        begin
            clk_en_cnt <= 3'b0;
            clk_en <= 1'b0;
        end
        else
        begin
            if (clk_en_cnt == (CLK_MHZ / VGA_CLOCK) - 1)
            begin 
                clk_en_cnt <= 3'b0;
                clk_en <= 1'b1;
            end
            else
            begin
                clk_en_cnt <= clk_en_cnt + 1;
                clk_en <= 1'b0;
            end
        end
    end

    // Making all outputs registered

    always_ff @ (posedge clk or posedge reset)
    begin
        if (reset)
        begin
            hsync       <= 1'b0;
            vsync       <= 1'b0;
            display_on  <= 1'b0;
            hpos        <= 1'b0;
            vpos        <= 1'b0;
        end
        else if (clk_en)
        begin
            hsync       <= ~ (    d_hpos >= H_SYNC_START
                               && d_hpos <= H_SYNC_END   );

            vsync       <= ~ (    d_vpos >= V_SYNC_START
                               && d_vpos <= V_SYNC_END   );

            display_on  <=   (    d_hpos <  H_DISPLAY
                               && d_vpos <  V_DISPLAY    );

            hpos        <= d_hpos;
            vpos        <= d_vpos;
        end
    end

endmodule

day_3/lab_03_vga/top.sv
module top
(
    input              clk,
    input              reset_n,

    input        [3:0] key_sw,
    output       [3:0] led,

    output       [7:0] abcdefgh,
    output       [3:0] digit,

    output             buzzer,

    output             hsync,
    output             vsync,
    output logic [2:0] rgb
);

    localparam X_WIDTH = 10,
               Y_WIDTH = 10,
               CLK_MHZ = 50;

    //------------------------------------------------------------------------

    assign led       = key_sw;
    assign abcdefgh  = 8'hff;
    assign digit     = 4'hf;
    assign buzzer    = 1'b0;

    //------------------------------------------------------------------------

    wire display_on;

    wire [X_WIDTH - 1:0] x;
    wire [Y_WIDTH - 1:0] y;
 
    vga
    # (
        .HPOS_WIDTH ( X_WIDTH      ),
        .VPOS_WIDTH ( Y_WIDTH      ),
        
        .CLK_MHZ    ( CLK_MHZ      )
    )
    i_vga
    (
        .clk        (   clk        ), 
        .reset      ( ~ reset_n    ),
        .hsync      (   hsync      ),
        .vsync      (   vsync      ),
        .display_on (   display_on ),
        .hpos       (   x          ),
        .vpos       (   y          )
    );

    //------------------------------------------------------------------------

    typedef enum bit [2:0]
    {
      black  = 3'b000,
      cyan   = 3'b011,
      red    = 3'b100,
      yellow = 3'b110,
      white  = 3'b111

      // TODO: Add other colors
    }
    rgb_t;

    always_comb
    begin
      // Circle

      if (~ display_on)
        rgb = black;
      else if (x ** 2 + y ** 2 < 100 ** 2)
        rgb = red;
      else if (x > 200 & y > 200 & x < 300 & y < 400) 
        rgb = yellow;
      else if (key_sw == 4'b1111 & (x - 600) ** 2 + (y - 200) ** 2 < 70 ** 2)
        rgb = white;
      else
        rgb = cyan;

      // TODO: Add other figures
    end

endmodule

day_4/sv/lab_05_7segment_word/tb.sv
module tb;

    logic       clk;
    logic       reset_n;
    logic [3:0] key_sw;

    top i_top
    (
        .clk     ( clk     ),
        .reset_n ( reset_n ),
        .key_sw  ( key_sw  )
    );

    initial
    begin
        clk = 1'b0;

        forever
            # 5 clk = ~ clk;
    end

    initial
    begin
        reset_n <= 1'bx;
        repeat (2) @ (posedge clk);
        reset_n <= 1'b0;
        repeat (2) @ (posedge clk);
        reset_n <= 1'b1;
    end

    initial
    begin

        `ifdef __ICARUS__
            $dumpvars;
        `endif

        key_sw <= 4'b0;

        @ (posedge reset_n);

        for (int i = 0; i < 50; i ++)
        begin
            // Enable override
 
            if (i == 20)
                force i_top.enable = 1'b1;
            else if (i == 40)
                release i_top.enable;

            @ (posedge clk);
            key_sw <= $random;
        end

        `ifdef MODEL_TECH  // Mentor ModelSim and Questa
            $stop;
        `else
            $finish;
        `endif
    end

endmodule

day_4/lab_03_vga/dump.vcd
$date
	Wed Sep 14 11:37:50 2022
$end
$version
	Icarus Verilog
$end
$timescale
	1s
$end
$scope module tb $end
$var reg 1 ! clk $end
$var reg 4 " key_sw [3:0] $end
$var reg 1 # reset_n $end
$scope module i_top $end
$var wire 8 $ abcdefgh [7:0] $end
$var wire 1 % buzzer $end
$var wire 1 ! clk $end
$var wire 4 & digit [3:0] $end
$var wire 4 ' key_sw [3:0] $end
$var wire 4 ( led [3:0] $end
$var wire 1 # reset_n $end
$var wire 10 ) y [9:0] $end
$var wire 10 * x [9:0] $end
$var wire 1 + vsync $end
$var wire 1 , hsync $end
$var wire 1 - display_on $end
$var reg 3 . rgb [2:0] $end
$scope module i_vga $end
$var wire 1 ! clk $end
$var wire 1 / reset $end
$var reg 1 0 clk_en $end
$var reg 4 1 clk_en_cnt [3:0] $end
$var reg 10 2 d_hpos [9:0] $end
$var reg 10 3 d_vpos [9:0] $end
$var reg 1 - display_on $end
$var reg 10 4 hpos [9:0] $end
$var reg 1 , hsync $end
$var reg 10 5 vpos [9:0] $end
$var reg 1 + vsync $end
$upscope $end
$upscope $end
$upscope $end
$enddefinitions $end
#0
$dumpvars
bx 5
bx 4
bx 3
bx 2
bx 1
x0
x/
b11 .
x-
x,
x+
bx *
bx )
b0 (
b0 '
b1111 &
0%
b11111111 $
x#
b0 "
0!
$end
#5
00
1!
#10
0!
#15
b0 3
b1 2
b0 .
b0 1
b0 )
b0 5
b0 *
b0 4
0-
0+
0,
1/
0#
1!
#20
0!
#25
1!
#30
0!
#35
0/
1#
1!
#40
0!
#45
b1 1
b100 (
b100 "
b100 '
1!
#50
0!
#55
10
b0 1
b1 (
b1 "
b1 '
1!
#60
0!
#65
b10 2
b100 .
b1 *
b1 4
1-
1+
1,
00
b1 1
b1001 (
b1001 "
b1001 '
1!
#70
0!
#75
10
b0 1
b11 (
b11 "
b11 '
1!
#80
0!
#85
b11 2
b10 *
b10 4
00
b1 1
b1101 (
b1101 "
b1101 '
1!
#90
0!
#95
10
b0 1
1!
#100
0!
#105
b100 2
b11 *
b11 4
00
b1 1
b101 (
b101 "
b101 '
1!
#110
0!
#115
10
b0 1
b10 (
b10 "
b10 '
1!
#120
0!
#125
b101 2
b100 *
b100 4
00
b1 1
b1 (
b1 "
b1 '
1!
#130
0!
#135
10
b0 1
b1101 (
b1101 "
b1101 '
1!
#140
0!
#145
b110 2
b101 *
b101 4
00
b1 1
b110 (
b110 "
b110 '
1!
#150
0!
#155
10
b0 1
b1101 (
b1101 "
b1101 '
1!
#160
0!
#165
b111 2
b110 *
b110 4
00
b1 1
1!
#170
0!
#175
10
b0 1
b1100 (
b1100 "
b1100 '
1!
#180
0!
#185
b1000 2
b111 *
b111 4
00
b1 1
b1001 (
b1001 "
b1001 '
1!
#190
0!
#195
10
b0 1
b110 (
b110 "
b110 '
1!
#200
0!
#205
b1001 2
b1000 *
b1000 4
00
b1 1
b101 (
b101 "
b101 '
1!
#210
0!
#215
10
b0 1
b1010 (
b1010 "
b1010 '
1!
#220
0!
#225
b1010 2
b1001 *
b1001 4
00
b1 1
b101 (
b101 "
b101 '
1!
#230
0!
#235
10
b0 1
b111 (
b111 "
b111 '
1!
#240
0!
#245
b1011 2
b1010 *
b1010 4
00
b1 1
b10 (
b10 "
b10 '
1!
#250
0!
#255
10
b0 1
b1111 (
b1111 "
b1111 '
1!
#260
0!
#265
b1100 2
b1011 *
b1011 4
00
b1 1
b10 (
b10 "
b10 '
1!
#270
0!
#275
10
b0 1
b1110 (
b1110 "
b1110 '
1!
#280
0!
#285
b1101 2
b1100 *
b1100 4
00
b1 1
b1000 (
b1000 "
b1000 '
1!
#290
0!
#295
10
b0 1
b101 (
b101 "
b101 '
1!
#300
0!
#305
b1110 2
b1101 *
b1101 4
00
b1 1
b1100 (
b1100 "
b1100 '
1!
#310
0!
#315
10
b0 1
b1101 (
b1101 "
b1101 '
1!
#320
0!
#325
b1111 2
b1110 *
b1110 4
00
b1 1
1!
#330
0!
#335
10
b0 1
b101 (
b101 "
b101 '
1!
#340
0!
#345
b10000 2
b1111 *
b1111 4
00
b1 1
b11 (
b11 "
b11 '
1!
#350
0!
#355
10
b0 1
b1010 (
b1010 "
b1010 '
1!
#360
0!
#365
b10001 2
b10000 *
b10000 4
00
b1 1
b0 (
b0 "
b0 '
1!
#370
0!
#375
10
b0 1
1!
#380
0!
#385
b10010 2
b10001 *
b10001 4
00
b1 1
b1010 (
b1010 "
b1010 '
1!
#390
0!
#395
10
b0 1
b1101 (
b1101 "
b1101 '
1!
#400
0!
#405
b10011 2
b10010 *
b10010 4
00
b1 1
b110 (
b110 "
b110 '
1!
#410
0!
#415
10
b0 1
b11 (
b11 "
b11 '
1!
#420
0!
#425
b10100 2
b10011 *
b10011 4
00
b1 1
b1101 (
b1101 "
b1101 '
1!
#430
0!
#435
10
b0 1
b11 (
b11 "
b11 '
1!
#440
0!
#445
b10101 2
b10100 *
b10100 4
00
b1 1
b1011 (
b1011 "
b1011 '
1!
#450
0!
#455
10
b0 1
b101 (
b101 "
b101 '
1!
#460
0!
#465
b10110 2
b10101 *
b10101 4
00
b1 1
b10 (
b10 "
b10 '
1!
#470
0!
#475
10
b0 1
b1110 (
b1110 "
b1110 '
1!
#480
0!
#485
b10111 2
b10110 *
b10110 4
00
b1 1
b1101 (
b1101 "
b1101 '
1!
#490
0!
#495
10
b0 1
b1111 (
b1111 "
b1111 '
1!
#500
0!
#505
b11000 2
b10111 *
b10111 4
00
b1 1
b11 (
b11 "
b11 '
1!
#510
0!
#515
10
b0 1
b1010 (
b1010 "
b1010 '
1!
#520
0!
#525
b11001 2
b11000 *
b11000 4
00
b1 1
1!
#530
0!
#535
10
b0 1
b1100 (
b1100 "
b1100 '
1!
#540
0!
#545
b11010 2
b11001 *
b11001 4
00
b1 1
b10 (
b10 "
b10 '
1!
#550
0!
#555
10
b0 1
b1010 (
b1010 "
b1010 '
1!
#560
0!
#565
b11011 2
b11010 *
b11010 4
00
b1 1
b1 (
b1 "
b1 '
1!
#570
0!
#575
10
b0 1
b1000 (
b1000 "
b1000 '
1!
#580
0!
#585
b11100 2
b11011 *
b11011 4
00
b1 1
1!
#590
0!
#595
10
b0 1
b1001 (
b1001 "
b1001 '
1!
#600
0!
#605
b11101 2
b11100 *
b11100 4
00
b1 1
b1011 (
b1011 "
b1011 '
1!
#610
0!
#615
10
b0 1
b110 (
b110 "
b110 '
1!
#620
0!
#625
b11110 2
b11101 *
b11101 4
00
b1 1
1!
#630
0!
#635
10
b0 1
b1110 (
b1110 "
b1110 '
1!
#640
0!
#645
b11111 2
b11110 *
b11110 4
00
b1 1
b1100 (
b1100 "
b1100 '
1!
#650
0!
#655
10
b0 1
b1010 (
b1010 "
b1010 '
1!
#660
0!
#665
b100000 2
b11111 *
b11111 4
00
b1 1
b1011 (
b1011 "
b1011 '
1!
#670
0!
#675
10
b0 1
b1 (
b1 "
b1 '
1!
#680
0!
#685
b100001 2
b100000 *
b100000 4
00
b1 1
b101 (
b101 "
b101 '
1!
#690
0!
#695
10
b0 1
b1111 (
b1111 "
b1111 '
1!
#700
0!
#705
b100010 2
b100001 *
b100001 4
00
b1 1
b1011 (
b1011 "
b1011 '
1!
#710
0!
#715
10
b0 1
b1010 (
b1010 "
b1010 '
1!
#720
0!
#725
b100011 2
b100010 *
b100010 4
00
b1 1
b1110 (
b1110 "
b1110 '
1!
#730
0!
#735
10
b0 1
b101 (
b101 "
b101 '
1!
#740
0!
#745
b100100 2
b100011 *
b100011 4
00
b1 1
b1 (
b1 "
b1 '
1!
#750
0!
#755
10
b0 1
b1001 (
b1001 "
b1001 '
1!
#760
0!
#765
b100101 2
b100100 *
b100100 4
00
b1 1
b10 (
b10 "
b10 '
1!
#770
0!
#775
10
b0 1
b1100 (
b1100 "
b1100 '
1!
#780
0!
#785
b100110 2
b100101 *
b100101 4
00
b1 1
b1111 (
b1111 "
b1111 '
1!
#790
0!
#795
10
b0 1
1!
#800
0!
#805
b100111 2
b100110 *
b100110 4
00
b1 1
b1000 (
b1000 "
b1000 '
1!
#810
0!
#815
10
b0 1
b111 (
b111 "
b111 '
1!
#820
0!
#825
b101000 2
b100111 *
b100111 4
00
b1 1
b1111 (
b1111 "
b1111 '
1!
#830
0!
#835
10
b0 1
b1100 (
b1100 "
b1100 '
1!
#840
0!
#845
b101001 2
b101000 *
b101000 4
00
b1 1
b1011 (
b1011 "
b1011 '
1!
#850
0!
#855
10
b0 1
b1001 (
b1001 "
b1001 '
1!
#860
0!
#865
b101010 2
b101001 *
b101001 4
00
b1 1
1!
#870
0!
#875
10
b0 1
b0 (
b0 "
b0 '
1!
#880
0!
#885
b101011 2
b101010 *
b101010 4
00
b1 1
b111 (
b111 "
b111 '
1!
#890
0!
#895
10
b0 1
b1 (
b1 "
b1 '
1!
#900
0!
#905
b101100 2
b101011 *
b101011 4
00
b1 1
b110 (
b110 "
b110 '
1!
#910
0!
#915
10
b0 1
b1100 (
b1100 "
b1100 '
1!
#920
0!
#925
b101101 2
b101100 *
b101100 4
00
b1 1
b10 (
b10 "
b10 '
1!
#930
0!
#935
10
b0 1
b1000 (
b1000 "
b1000 '
1!
#940
0!
#945
b101110 2
b101101 *
b101101 4
00
b1 1
b111 (
b111 "
b111 '
1!
#950
0!
#955
10
b0 1
b1101 (
b1101 "
b1101 '
1!
#960
0!
#965
b101111 2
b101110 *
b101110 4
00
b1 1
b10 (
b10 "
b10 '
1!
#970
0!
#975
10
b0 1
b1110 (
b1110 "
b1110 '
1!
#980
0!
#985
b110000 2
b101111 *
b101111 4
00
b1 1
b1101 (
b1101 "
b1101 '
1!
#990
0!
#995
10
b0 1
b1001 (
b1001 "
b1001 '
1!
#1000
0!
#1005
b110001 2
b110000 *
b110000 4
00
b1 1
b1111 (
b1111 "
b1111 '
1!
#1010
0!
#1015
10
b0 1
b11 (
b11 "
b11 '
1!
#1020
0!
#1025
b110010 2
b110001 *
b110001 4
00
b1 1
b101 (
b101 "
b101 '
1!
#1030
0!
#1035
10
b0 1
b1000 (
b1000 "
b1000 '
1!
#1040
0!
#1045
b110011 2
b110010 *
b110010 4
00
b1 1
b1011 (
b1011 "
b1011 '
1!
#1050
0!
#1055
10
b0 1
b1001 (
b1001 "
b1001 '
1!
#1060
0!
#1065
b110100 2
b110011 *
b110011 4
00
b1 1
b1111 (
b1111 "
b1111 '
1!
#1070
0!
#1075
10
b0 1
b1010 (
b1010 "
b1010 '
1!
#1080
0!
#1085
b110101 2
b110100 *
b110100 4
00
b1 1
b1000 (
b1000 "
b1000 '
1!
#1090
0!
#1095
10
b0 1
b110 (
b110 "
b110 '
1!
#1100
0!
#1105
b110110 2
b110101 *
b110101 4
00
b1 1
b1110 (
b1110 "
b1110 '
1!
#1110
0!
#1115
10
b0 1
b1100 (
b1100 "
b1100 '
1!
#1120
0!
#1125
b110111 2
b110110 *
b110110 4
00
b1 1
b1010 (
b1010 "
b1010 '
1!
#1130
0!
#1135
10
b0 1
b110 (
b110 "
b110 '
1!
#1140
0!
#1145
b111000 2
b110111 *
b110111 4
00
b1 1
b11 (
b11 "
b11 '
1!
#1150
0!
#1155
10
b0 1
1!
#1160
0!
#1165
b111001 2
b111000 *
b111000 4
00
b1 1
b1111 (
b1111 "
b1111 '
1!
#1170
0!
#1175
10
b0 1
b11 (
b11 "
b11 '
1!
#1180
0!
#1185
b111010 2
b111001 *
b111001 4
00
b1 1
b1111 (
b1111 "
b1111 '
1!
#1190
0!
#1195
10
b0 1
b100 (
b100 "
b100 '
1!
#1200
0!
#1205
b111011 2
b111010 *
b111010 4
00
b1 1
b111 (
b111 "
b111 '
1!
#1210
0!
#1215
10
b0 1
b1011 (
b1011 "
b1011 '
1!
#1220
0!
#1225
b111100 2
b111011 *
b111011 4
00
b1 1
b110 (
b110 "
b110 '
1!
#1230
0!
#1235
10
b0 1
b1010 (
b1010 "
b1010 '
1!
#1240
0!
#1245
b111101 2
b111100 *
b111100 4
00
b1 1
b1001 (
b1001 "
b1001 '
1!
#1250
0!
#1255
10
b0 1
b1101 (
b1101 "
b1101 '
1!
#1260
0!
#1265
b111110 2
b111101 *
b111101 4
00
b1 1
b1010 (
b1010 "
b1010 '
1!
#1270
0!
#1275
10
b0 1
b101 (
b101 "
b101 '
1!
#1280
0!
#1285
b111111 2
b111110 *
b111110 4
00
b1 1
1!
#1290
0!
#1295
10
b0 1
b1111 (
b1111 "
b1111 '
1!
#1300
0!
#1305
b1000000 2
b111111 *
b111111 4
00
b1 1
b1001 (
b1001 "
b1001 '
1!
#1310
0!
#1315
10
b0 1
b100 (
b100 "
b100 '
1!
#1320
0!
#1325
b1000001 2
b1000000 *
b1000000 4
00
b1 1
b0 (
b0 "
b0 '
1!
#1330
0!
#1335
10
b0 1
b1010 (
b1010 "
b1010 '
1!
#1340
0!
#1345
b1000010 2
b1000001 *
b1000001 4
00
b1 1
b1011 (
b1011 "
b1011 '
1!
#1350
0!
#1355
10
b0 1
b1110 (
b1110 "
b1110 '
1!
#1360
0!
#1365
b1000011 2
b1000010 *
b1000010 4
00
b1 1
b1100 (
b1100 "
b1100 '
1!
#1370
0!
#1375
10
b0 1
b1010 (
b1010 "
b1010 '
1!
#1380
0!
#1385
b1000100 2
b1000011 *
b1000011 4
00
b1 1
b1101 (
b1101 "
b1101 '
1!
#1390
0!
#1395
10
b0 1
b11 (
b11 "
b11 '
1!
#1400
0!
#1405
b1000101 2
b1000100 *
b1000100 4
00
b1 1
b110 (
b110 "
b110 '
1!
#1410
0!
#1415
10
b0 1
b1110 (
b1110 "
b1110 '
1!
#1420
0!
#1425
b1000110 2
b1000101 *
b1000101 4
00
b1 1
b111 (
b111 "
b111 '
1!
#1430
0!
#1435
10
b0 1
b1010 (
b1010 "
b1010 '
1!
#1440
0!
#1445
b1000111 2
b1000110 *
b1000110 4
00
b1 1
b110 (
b110 "
b110 '
1!
#1450
0!
#1455
10
b0 1
b1000 (
b1000 "
b1000 '
1!
#1460
0!
#1465
b1001000 2
b1000111 *
b1000111 4
00
b1 1
b1001 (
b1001 "
b1001 '
1!
#1470
0!
#1475
10
b0 1
b1000 (
b1000 "
b1000 '
1!
#1480
0!
#1485
b1001001 2
b1001000 *
b1001000 4
00
b1 1
b100 (
b100 "
b100 '
1!
#1490
0!
#1495
10
b0 1
b11 (
b11 "
b11 '
1!
#1500
0!
#1505
b1001010 2
b1001001 *
b1001001 4
00
b1 1
b100 (
b100 "
b100 '
1!
#1510
0!
#1515
10
b0 1
b1001 (
b1001 "
b1001 '
1!
#1520
0!
#1525
b1001011 2
b1001010 *
b1001010 4
00
b1 1
b1011 (
b1011 "
b1011 '
1!
#1530
0!
#1535
10
b0 1
b1101 (
b1101 "
b1101 '
1!
#1540
0!
#1545
b1001100 2
b1001011 *
b1001011 4
00
b1 1
b1001 (
b1001 "
b1001 '
1!
#1550
0!
#1555
10
b0 1
b1101 (
b1101 "
b1101 '
1!
#1560
0!
#1565
b1001101 2
b1001100 *
b1001100 4
00
b1 1
b110 (
b110 "
b110 '
1!
#1570
0!
#1575
10
b0 1
b1010 (
b1010 "
b1010 '
1!
#1580
0!
#1585
b1001110 2
b1001101 *
b1001101 4
00
b1 1
b110 (
b110 "
b110 '
1!
#1590
0!
#1595
10
b0 1
b101 (
b101 "
b101 '
1!
#1600
0!
#1605
b1001111 2
b1001110 *
b1001110 4
00
b1 1
b110 (
b110 "
b110 '
1!
#1610
0!
#1615
10
b0 1
b100 (
b100 "
b100 '
1!
#1620
0!
#1625
b1010000 2
b1001111 *
b1001111 4
00
b1 1
b111 (
b111 "
b111 '
1!
#1630
0!
#1635
10
b0 1
b1001 (
b1001 "
b1001 '
1!
#1640
0!
#1645
b1010001 2
b1010000 *
b1010000 4
00
b1 1
b100 (
b100 "
b100 '
1!
#1650
0!
#1655
10
b0 1
b1000 (
b1000 "
b1000 '
1!
#1660
0!
#1665
b1010010 2
b1010001 *
b1010001 4
00
b1 1
1!
#1670
0!
#1675
10
b0 1
b1101 (
b1101 "
b1101 '
1!
#1680
0!
#1685
b1010011 2
b1010010 *
b1010010 4
00
b1 1
b111 (
b111 "
b111 '
1!
#1690
0!
#1695
10
b0 1
b1110 (
b1110 "
b1110 '
1!
#1700
0!
#1705
b1010100 2
b1010011 *
b1010011 4
00
b1 1
b1000 (
b1000 "
b1000 '
1!
#1710
0!
#1715
10
b0 1
b1100 (
b1100 "
b1100 '
1!
#1720
0!
#1725
b1010101 2
b1010100 *
b1010100 4
00
b1 1
b1101 (
b1101 "
b1101 '
1!
#1730
0!
#1735
10
b0 1
b1001 (
b1001 "
b1001 '
1!
#1740
0!
#1745
b1010110 2
b1010101 *
b1010101 4
00
b1 1
b1100 (
b1100 "
b1100 '
1!
#1750
0!
#1755
10
b0 1
b110 (
b110 "
b110 '
1!
#1760
0!
#1765
b1010111 2
b1010110 *
b1010110 4
00
b1 1
b1010 (
b1010 "
b1010 '
1!
#1770
0!
#1775
10
b0 1
b1101 (
b1101 "
b1101 '
1!
#1780
0!
#1785
b1011000 2
b1010111 *
b1010111 4
00
b1 1
b110 (
b110 "
b110 '
1!
#1790
0!
#1795
10
b0 1
b0 (
b0 "
b0 '
1!
#1800
0!
#1805
b1011001 2
b1011000 *
b1011000 4
00
b1 1
b11 (
b11 "
b11 '
1!
#1810
0!
#1815
10
b0 1
b1010 (
b1010 "
b1010 '
1!
#1820
0!
#1825
b1011010 2
b1011001 *
b1011001 4
00
b1 1
b1110 (
b1110 "
b1110 '
1!
#1830
0!
#1835
10
b0 1
b1010 (
b1010 "
b1010 '
1!
#1840
0!
#1845
b1011011 2
b1011010 *
b1011010 4
00
b1 1
b101 (
b101 "
b101 '
1!
#1850
0!
#1855
10
b0 1
b1010 (
b1010 "
b1010 '
1!
#1860
0!
#1865
b1011100 2
b1011011 *
b1011011 4
00
b1 1
b1001 (
b1001 "
b1001 '
1!
#1870
0!
#1875
10
b0 1
b111 (
b111 "
b111 '
1!
#1880
0!
#1885
b1011101 2
b1011100 *
b1011100 4
00
b1 1
b110 (
b110 "
b110 '
1!
#1890
0!
#1895
10
b0 1
b0 (
b0 "
b0 '
1!
#1900
0!
#1905
b1011110 2
b1011101 *
b1011101 4
00
b1 1
b110 (
b110 "
b110 '
1!
#1910
0!
#1915
10
b0 1
1!
#1920
0!
#1925
b1011111 2
b1011110 *
b1011110 4
00
b1 1
b1101 (
b1101 "
b1101 '
1!
#1930
0!
#1935
10
b0 1
b1100 (
b1100 "
b1100 '
1!
#1940
0!
#1945
b1100000 2
b1011111 *
b1011111 4
00
b1 1
b110 (
b110 "
b110 '
1!
#1950
0!
#1955
10
b0 1
b1000 (
b1000 "
b1000 '
1!
#1960
0!
#1965
b1100001 2
b1100000 *
b1100000 4
00
b1 1
b1110 (
b1110 "
b1110 '
1!
#1970
0!
#1975
10
b0 1
b1011 (
b1011 "
b1011 '
1!
#1980
0!
#1985
b1100010 2
b1100001 *
b1100001 4
00
b1 1
b1111 (
b1111 "
b1111 '
1!
#1990
0!
#1995
10
b0 1
b1001 (
b1001 "
b1001 '
1!
#2000
0!
#2005
b1100011 2
b1100010 *
b1100010 4
00
b1 1
b1010 (
b1010 "
b1010 '
1!
#2010
0!
#2015
10
b0 1
b1 (
b1 "
b1 '
1!
#2020
0!
#2025
b1100100 2
b1100011 *
b1100011 4
00
b1 1
b111 (
b111 "
b111 '
1!
#2030
0!
#2035
10
b0 1
b1 (
b1 "
b1 '
1!
#2040
0!
#2045
b1100101 2
b11 .
b1100100 *
b1100100 4
00
b1 1
b110 (
b110 "
b110 '
1!
#2050
0!
#2055
10
b0 1
b0 (
b0 "
b0 '
1!
#2060
0!
#2065
b1100110 2
b1100101 *
b1100101 4
00
b1 1
b101 (
b101 "
b101 '
1!
#2070
0!
#2075
10
b0 1
1!
#2080
0!
#2085
b1100111 2
b1100110 *
b1100110 4
00
b1 1
b1001 (
b1001 "
b1001 '
1!
#2090
0!
#2095
10
b0 1
b1 (
b1 "
b1 '
1!
#2100
0!
#2105
b1101000 2
b1100111 *
b1100111 4
00
b1 1
b101 (
b101 "
b101 '
1!
#2110
0!
#2115
10
b0 1
b1000 (
b1000 "
b1000 '
1!
#2120
0!
#2125
b1101001 2
b1101000 *
b1101000 4
00
b1 1
b1011 (
b1011 "
b1011 '
1!
#2130
0!
#2135
10
b0 1
b11 (
b11 "
b11 '
1!
#2140
0!
#2145
b1101010 2
b1101001 *
b1101001 4
00
b1 1
b1100 (
b1100 "
b1100 '
1!
#2150
0!
#2155
10
b0 1
b1010 (
b1010 "
b1010 '
1!
#2160
0!
#2165
b1101011 2
b1101010 *
b1101010 4
00
b1 1
b1110 (
b1110 "
b1110 '
1!
#2170
0!
#2175
10
b0 1
b1000 (
b1000 "
b1000 '
1!
#2180
0!
#2185
b1101100 2
b1101011 *
b1101011 4
00
b1 1
b1001 (
b1001 "
b1001 '
1!
#2190
0!
#2195
10
b0 1
b1 (
b1 "
b1 '
1!
#2200
0!
#2205
b1101101 2
b1101100 *
b1101100 4
00
b1 1
b1110 (
b1110 "
b1110 '
1!
#2210
0!
#2215
10
b0 1
b110 (
b110 "
b110 '
1!
#2220
0!
#2225
b1101110 2
b1101101 *
b1101101 4
00
b1 1
b1111 (
b1111 "
b1111 '
1!
#2230
0!
#2235
10
b0 1
b1010 (
b1010 "
b1010 '
1!
#2240
0!
#2245
b1101111 2
b1101110 *
b1101110 4
00
b1 1
1!
#2250
0!
#2255
10
b0 1
b1101 (
b1101 "
b1101 '
1!
#2260
0!
#2265
b1110000 2
b1101111 *
b1101111 4
00
b1 1
b1110 (
b1110 "
b1110 '
1!
#2270
0!
#2275
10
b0 1
b1000 (
b1000 "
b1000 '
1!
#2280
0!
#2285
b1110001 2
b1110000 *
b1110000 4
00
b1 1
b1001 (
b1001 "
b1001 '
1!
#2290
0!
#2295
10
b0 1
b1000 (
b1000 "
b1000 '
1!
#2300
0!
#2305
b1110010 2
b1110001 *
b1110001 4
00
b1 1
b1010 (
b1010 "
b1010 '
1!
#2310
0!
#2315
10
b0 1
b11 (
b11 "
b11 '
1!
#2320
0!
#2325
b1110011 2
b1110010 *
b1110010 4
00
b1 1
b1011 (
b1011 "
b1011 '
1!
#2330
0!
#2335
10
b0 1
b111 (
b111 "
b111 '
1!
#2340
0!
#2345
b1110100 2
b1110011 *
b1110011 4
00
b1 1
b110 (
b110 "
b110 '
1!
#2350
0!
#2355
10
b0 1
b1010 (
b1010 "
b1010 '
1!
#2360
0!
#2365
b1110101 2
b1110100 *
b1110100 4
00
b1 1
b100 (
b100 "
b100 '
1!
#2370
0!
#2375
10
b0 1
b1001 (
b1001 "
b1001 '
1!
#2380
0!
#2385
b1110110 2
b1110101 *
b1110101 4
00
b1 1
b10 (
b10 "
b10 '
1!
#2390
0!
#2395
10
b0 1
b100 (
b100 "
b100 '
1!
#2400
0!
#2405
b1110111 2
b1110110 *
b1110110 4
00
b1 1
b1111 (
b1111 "
b1111 '
1!
#2410
0!
#2415
10
b0 1
b110 (
b110 "
b110 '
1!
#2420
0!
#2425
b1111000 2
b1110111 *
b1110111 4
00
b1 1
b1010 (
b1010 "
b1010 '
1!
#2430
0!
#2435
10
b0 1
b10 (
b10 "
b10 '
1!
#2440
0!
#2445
b1111001 2
b1111000 *
b1111000 4
00
b1 1
1!
#2450
0!
#2455
10
b0 1
b1101 (
b1101 "
b1101 '
1!
#2460
0!
#2465
b1111010 2
b1111001 *
b1111001 4
00
b1 1
b100 (
b100 "
b100 '
1!
#2470
0!
#2475
10
b0 1
1!
#2480
0!
#2485
b1111011 2
b1111010 *
b1111010 4
00
b1 1
b1010 (
b1010 "
b1010 '
1!
#2490
0!
#2495
10
b0 1
b1001 (
b1001 "
b1001 '
1!
#2500
0!
#2505
b1111100 2
b1111011 *
b1111011 4
00
b1 1
b1 (
b1 "
b1 '
1!
#2510
0!
#2515
10
b0 1
b1110 (
b1110 "
b1110 '
1!
#2520
0!
#2525
b1111101 2
b1111100 *
b1111100 4
00
b1 1
b1011 (
b1011 "
b1011 '
1!
#2530
0!
#2535
10
b0 1
1!
#2540
0!
#2545
b1111110 2
b1111101 *
b1111101 4
00
b1 1
b1111 (
b1111 "
b1111 '
1!
