day_4/sv/lab_01_and_or_xor/top.sv
module top
(
    input        clk,
    input        reset_n,
    
    input  [3:0] key_sw,
    output [3:0] led,

    output [7:0] abcdefgh,
    output [3:0] digit,

    output       buzzer,

    output       hsync,
    output       vsync,
    output [2:0] rgb
);

    assign abcdefgh  = 8'hff;
    assign digit     = 4'hf;
    assign buzzer    = 1'b0;
    assign hsync     = 1'b1;
    assign vsync     = 1'b1;
    assign rgb       = 3'b0;

    wire a = ~ key_sw [0];
    wire b = ~ key_sw [1];
    
    wire result = a ^ b;

    assign led [0] = ~ result;
    
    assign led [1] = ~ (~ key_sw [0] ^ ~ key_sw [1]);

    // Exercise 1: Change the code below.
    // Assign to led [2] the result of AND operation
    
    assign led [2] = 1'b0;

    // Exercise 2: Change the code below.
    // Assign to led [3] the result of XOR operation
    // without using "^" operation.
    // Use only operations "&", "|", "~" and parenthesis, "(" and ")".

    assign led [3] = 1'b0;

endmodule

day_4/lab_02_7segment_letter/tb.sv
module tb;

    logic [3:0] key_sw;

    top i_top (.key_sw (key_sw));

    initial
    begin
        $dumpvars;

        repeat (8) #10 key_sw <= $random;

        `ifdef MODEL_TECH  // Mentor ModelSim and Questa
            $stop;
        `else
            $finish;
        `endif
    end

endmodule

day_4/lab_01_and_or_xor/dump.vcd
$date
	Wed Sep 14 11:37:01 2022
$end
$version
	Icarus Verilog
$end
$timescale
	1s
$end
$scope module tb $end
$var reg 4 ! key_sw [3:0] $end
$scope module i_top $end
$var wire 1 " a $end
$var wire 8 # abcdefgh [7:0] $end
$var wire 1 $ b $end
$var wire 1 % buzzer $end
$var wire 1 & clk $end
$var wire 4 ' digit [3:0] $end
$var wire 1 ( hsync $end
$var wire 4 ) key_sw [3:0] $end
$var wire 1 * reset_n $end
$var wire 1 + result $end
$var wire 3 , rgb [2:0] $end
$var wire 1 - vsync $end
$var wire 4 . led [3:0] $end
$upscope $end
$upscope $end
$enddefinitions $end
#0
$dumpvars
b0xx .
1-
b0 ,
x+
z*
bx )
1(
b1111 '
z&
0%
x$
b11111111 #
x"
bx !
$end
#10
b11 .
0+
1"
1$
b100 !
b100 )
#20
b0 .
1+
0"
b1 !
b1 )
#30
b1001 !
b1001 )
#40
b11 .
0+
0$
b11 !
b11 )
#50
b0 .
1+
1$
b1101 !
b1101 )
#70
b101 !
b101 )
#80
1"
0$
b10 !
b10 )
